calnex_paragon/CalnexRest.py
calnex_paragon/__init__.py
calnex_paragon/check.py
calnex_paragon/paragon.py
calnex_paragon/test_connect.py
calnex_paragon/test_replay.py
calnex_paragon/test_simple.py
calnex_paragon/test_tcl.py
calnex_paragon-0.0.1.data/scripts/paragon.py
calnex_paragon-0.0.1.dist-info/METADATA
calnex_paragon-0.0.1.dist-info/WHEEL
calnex_paragon-0.0.1.dist-info/top_level.txt
calnex_paragon-0.0.1.dist-info/RECORD
