Metadata-Version: 2.1
Name: calnex-paragon
Version: 0.0.1
Summary: Calnex Paragon Libraries. Content is copyright of calnexThis is just a pip version of the same
Home-page: http://packages.python.org/calnex-paragon
Author: Manali Gupta
Author-email: manligup@cisco.com
License: BSD
Keywords: Calnex Paragon Timing
Platform: UNKNOWN
Classifier: Development Status :: 3 - Alpha
Classifier: Topic :: Utilities
Classifier: License :: OSI Approved :: BSD License
